respectify/__init__.py
respectify/_base.py
respectify/client.py
respectify/client_async.py
respectify/exceptions.py
respectify/schemas.py
respectify-0.2.2.dist-info/METADATA
respectify-0.2.2.dist-info/WHEEL
respectify-0.2.2.dist-info/RECORD
